./.gitignore
./PKG-INFO
./README.md
./pyproject.toml
./uv.lock
./temporalcodec/encryption.py
./temporalcodec/py.typed
temporalcodec-0.4.3.dist-info/METADATA
temporalcodec-0.4.3.dist-info/WHEEL
temporalcodec-0.4.3.dist-info/RECORD
