Metadata-Version: 2.4
Name: temporalcodec
Version: 0.4.3
Summary: Encode and decode your Temporal data
Project-URL: Homepage, https://github.com/mrsimonemms/temporal-codec-server
Project-URL: Repository, https://github.com/mrsimonemms/temporal-codec-server
Project-URL: Documentation, https://github.com/mrsimonemms/temporal-codec-server
Project-URL: Bug Tracker, https://github.com/mrsimonemms/temporal-codec-server/issues
Author-email: Simon Emms <simon@simonemms.com>
License: Apache-2.0
Keywords: codec,decoding,decryption,encoding,encryption,temporal,workflow
Requires-Python: >=3.9
